MANIFEST.in
README.md
setup.py
bin/mirbot
images/mirbot.png
images/mirbot.svg
mirbot/__init__.py
mirbot/defaults.py
mirbot.egg-info/PKG-INFO
mirbot.egg-info/SOURCES.txt
mirbot.egg-info/dependency_links.txt
mirbot.egg-info/not-zip-safe
mirbot.egg-info/requires.txt
mirbot.egg-info/top_level.txt
mirbot/modules/afk.py
mirbot/modules/basic.py
mirbot/modules/example.py