Metadata-Version: 1.1
Name: mirbot
Version: 3.0.2
Summary: Modular Information Retrieval Bot (MIRbot)
Home-page: https://github.com/pyratlabs/mirbot
Author: PyratLabs
Author-email: git@xan-manning.co.uk
License: MIT
Platform: UNKNOWN
Classifier: Programming Language :: Python
Classifier: Programming Language :: Python :: 3
